immunix/__init__.py
immunix/core.py
immunix/exceptions.py
immunix/genome.py
immunix/strategies.py
immunix/vault.py
immunix_core-0.1.0.dist-info/licenses/LICENSE
immunix_core-0.1.0.dist-info/METADATA
immunix_core-0.1.0.dist-info/WHEEL
immunix_core-0.1.0.dist-info/top_level.txt
immunix_core-0.1.0.dist-info/RECORD
