Metadata-Version: 2.4
Name: immunix-core
Version: 0.1.0
Summary: Autonomous Self-Healing Infrastructure for Critical Python Systems
Author: Mohamed Orhan Zeinel
License: MIT
Requires-Python: >=3.9
License-File: LICENSE
Dynamic: license-file
